cloudshell/__init__.py
cloudshell/iac/__init__.py
cloudshell/iac/terraform/__init__.py
cloudshell/iac/terraform/constants.py
cloudshell/iac/terraform/terraform_shell.py
cloudshell/iac/terraform/downloaders/__init__.py
cloudshell/iac/terraform/downloaders/base_git_downloader.py
cloudshell/iac/terraform/downloaders/downloader.py
cloudshell/iac/terraform/downloaders/github_downloader.py
cloudshell/iac/terraform/downloaders/gitlab_downloader.py
cloudshell/iac/terraform/downloaders/tf_exec_downloader.py
cloudshell/iac/terraform/models/__init__.py
cloudshell/iac/terraform/models/config.py
cloudshell/iac/terraform/models/exceptions.py
cloudshell/iac/terraform/models/shell_helper.py
cloudshell/iac/terraform/models/tf_service.py
cloudshell/iac/terraform/services/__init__.py
cloudshell/iac/terraform/services/backend_handler.py
cloudshell/iac/terraform/services/clp_envvar_handler.py
cloudshell/iac/terraform/services/gitlab_api_handler.py
cloudshell/iac/terraform/services/input_output_service.py
cloudshell/iac/terraform/services/live_status_updater.py
cloudshell/iac/terraform/services/local_dir_service.py
cloudshell/iac/terraform/services/object_factory.py
cloudshell/iac/terraform/services/provider_handler.py
cloudshell/iac/terraform/services/sandbox_messages.py
cloudshell/iac/terraform/services/sandox_data.py
cloudshell/iac/terraform/services/string_cleaner.py
cloudshell/iac/terraform/services/svc_attribute_handler.py
cloudshell/iac/terraform/services/tf_proc_exec.py
cloudshell/iac/terraform/tagging/__init__.py
cloudshell/iac/terraform/tagging/tag_terraform_resources.py
cloudshell/iac/terraform/tagging/tags.py
tests/__init__.py
tests/constants.py
tests/integration_tests/__init__.py
tests/integration_tests/int_test_downloader.py
tests/integration_tests/test_gitlab_downloader.py
tests/integration_tests/helper_objects/__init__.py
tests/integration_tests/helper_objects/env_vars.py
tests/integration_tests/helper_objects/integration_context.py
cloudshell_iac_terraform-1.3.0.dist-info/METADATA
cloudshell_iac_terraform-1.3.0.dist-info/WHEEL
cloudshell_iac_terraform-1.3.0.dist-info/top_level.txt
cloudshell_iac_terraform-1.3.0.dist-info/RECORD
